certbot_plugin_edgedns/__init__.py
certbot_plugin_edgedns/edgedns.py
certbot_plugin_edgedns/edgedns_test.py
certbot_plugin_edgedns-0.1.0.dist-info/LICENSE.txt
certbot_plugin_edgedns-0.1.0.dist-info/METADATA
certbot_plugin_edgedns-0.1.0.dist-info/WHEEL
certbot_plugin_edgedns-0.1.0.dist-info/entry_points.txt
certbot_plugin_edgedns-0.1.0.dist-info/top_level.txt
certbot_plugin_edgedns-0.1.0.dist-info/RECORD
