Metadata-Version: 2.1
Name: certbot-plugin-edgedns
Version: 0.1.0
Summary: Akamai Edge DNS Authenticator plugin for Certbot
Home-page: https://github.com/akamai/certbot-plugin-edgedns
Author: Ed Lynes [Akamai Technologies, Inc]
Author-email: elynes@akamai.com
License: Apache License 2.0
Keywords: certbot,edgedns
Platform: UNKNOWN
Classifier: Development Status :: 3 - Alpha
Classifier: Environment :: Plugins
Classifier: Intended Audience :: System Administrators
Classifier: License :: OSI Approved :: Apache Software License
Classifier: Operating System :: POSIX :: Linux
Classifier: Programming Language :: Python
Classifier: Programming Language :: Python :: 2
Classifier: Programming Language :: Python :: 2.7
Classifier: Programming Language :: Python :: 3
Classifier: Programming Language :: Python :: 3.5
Classifier: Programming Language :: Python :: 3.6
Classifier: Programming Language :: Python :: 3.7
Classifier: Programming Language :: Python :: 3.8
Classifier: Topic :: Internet :: WWW/HTTP
Classifier: Topic :: Security
Classifier: Topic :: System :: Installation/Setup
Classifier: Topic :: System :: Networking
Classifier: Topic :: System :: Systems Administration
Classifier: Topic :: Utilities
Requires-Python: >=2.7, !=3.0.*, !=3.1.*, !=3.2.*, !=3.3.*, !=3.4.*
Requires-Dist: acme (>=0.29.0)
Requires-Dist: certbot (>=1.1.0)
Requires-Dist: setuptools
Requires-Dist: requests
Requires-Dist: mock
Requires-Dist: urllib3
Requires-Dist: edgegrid-python (>=1.1.1)
Provides-Extra: docs
Requires-Dist: Sphinx (>=1.0) ; extra == 'docs'
Requires-Dist: sphinx-rtd-theme ; extra == 'docs'
